<?xml version="1.0" encoding="utf-8"?>
<odoo>
  <data>
    <record model="res.groups" id="sh_purchase_mod.group_show_backorder">
        <field name="name">Show Backorders</field>
        <field name="category_id" ref="base.module_category_hidden"/>
    </record>
    <record model="res.groups" id="sh_purchase_mod.group_show_returns">
        <field name="name">Show Returns</field>
        <field name="category_id" ref="base.module_category_hidden"/>
    </record>
    <record model="res.groups" id="sh_purchase_mod.group_show_scrapped">
        <field name="name">Show Scrapped</field>
        <field name="category_id" ref="base.module_category_hidden"/>
    </record>
  </data>
</odoo>
